type_check/__init__.py
type_check/type_check.py
type_check-0.1.8.dist-info/DESCRIPTION.rst
type_check-0.1.8.dist-info/METADATA
type_check-0.1.8.dist-info/RECORD
type_check-0.1.8.dist-info/WHEEL
type_check-0.1.8.dist-info/metadata.json
type_check-0.1.8.dist-info/top_level.txt
