Metadata-Version: 2.0
Name: type-check
Version: 0.1.8
Summary: Type check decorator for python
Home-page: UNKNOWN
License: UNKNOWN
Keywords: type check safe
Platform: UNKNOWN
Classifier: License :: OSI Approved :: MIT License
Classifier: Programming Language :: Python :: 3.4
Classifier: Programming Language :: Python :: 3.5
Classifier: Programming Language :: Python :: 3.6
